lektor_jsminify.py
lektor_jsminify-1.4.1.dist-info/LICENSE
lektor_jsminify-1.4.1.dist-info/METADATA
lektor_jsminify-1.4.1.dist-info/WHEEL
lektor_jsminify-1.4.1.dist-info/entry_points.txt
lektor_jsminify-1.4.1.dist-info/top_level.txt
lektor_jsminify-1.4.1.dist-info/RECORD
