Metadata-Version: 2.1
Name: lektor-jsminify
Version: 1.4.1
Summary: JS minifier for Lektor. Based on rjsmin.
Home-page: https://github.com/maxbachmann/lektor-JSminify
Author: maxbachmann
Author-email: kontakt@maxbachmann.de
License: MIT
Keywords: Lektor plugin
Platform: UNKNOWN
Classifier: Development Status :: 5 - Production/Stable
Classifier: Framework :: Lektor
Classifier: Environment :: Plugins
Classifier: Intended Audience :: Developers
Classifier: License :: OSI Approved :: MIT License
Classifier: Programming Language :: Python :: 3
Requires-Dist: rjsmin
Requires-Dist: termcolor
